[
  {
    "timestamp": "2026-05-28T09:19:10.800081",
    "is_trade": true,
    "direction": "BULLISH",
    "trade_signal": "BUY 23900 CE",
    "adjusted_score": 73,
    "base_score": 68,
    "confidence_level": "HIGH",
    "alignment_summary": "2/3 BULLISH aligned | 5m:BULLISH | 15m:BULLISH | 1h:SIDEWAYS",
    "price": 23921.6,
    "vwap": 23920.45,
    "ema9": 23906.2,
    "oi_result": {
      "score_adjustment": 0,
      "pcr": null,
      "max_pain": null,
      "atm_bias": "NEUTRAL",
      "valid": false,
      "error": "Option chain fetch failed",
      "source": "none"
    },
    "sent_result": {
      "total_adjustment": 5,
      "vix": 14.98,
      "vix_adjustment": 5,
      "us_futures_pct": -0.26,
      "futures_adjustment": 0,
      "sentiment": "NEUTRAL",
      "sentiment_adjustment": 0,
      "bullish_headlines": 8,
      "bearish_headlines": 6,
      "total_headlines": 14,
      "labels": [
        "VIX=15.0 [CALM <15 \u2192 +5]",
        "ES=F -0.26% [FLAT \u2192 0]",
        "Sentiment: NEUTRAL (8B/6b)"
      ],
      "valid": true,
      "cached": false,
      "_raw_headlines": [
        "Taking Stock: Market fails to hold on to day#39;s gains, ends marginally higher",
        "Sensex, Nifty gain for third day in a row; easing volatility to support bull trend",
        "Mid-day Mood | Cooling volatility sparks market rally, India VIX sees steepest fall in 4 years",
        "Sensex, Nifty extend gains to 3rd day, Q4 results to guide stock-specific action",
        "Gold sinks to 2-month low as US-Iran tensions stoke inflation fears",
        "Asia shares take a breather as Gulf hostilities drag on",
        "South Korean stocks at risk of 'swift downside reversal' as SK Hynix, Samsung dominate: BTIG",
        "Ather Energy enters insurance segment with new subsidiary Ather Insurance",
        "RITES signs MoU with Crisil to develop data-driven infrastructure consultancy solutions",
        "PG Electroplast profit slumps 55% as weak AC demand, West Asia-linked disruptions hit business",
        "S&P 500, Nasdaq retreat from records as tech momentum fades, oil trims losses amid US-Iran talks",
        "Enviro Infra subsidiary bags \u20b9207-crore hybrid renewable EPC contract",
        "PC Jeweller Q4 sparkles with 61% profit surge as revenue grows 33%",
        "Bata India Q4 margins contract as VRS expense dents profit; revenue rises 5%",
        "Stock Market Highlights, Sensex Today: Sensex Falls 100 Points Amid Uncertainty Over US-Iran Deal - NDTV",
        "Sensex Today | Nifty 50 | Stock Market Highlights: Sensex snaps 3-day losing run, ends 639 pts higher; Ni... - The Economic Times",
        "Closing Bell: Sell-off deepens: Nifty breaches 24,200, Sensex plunges 900 pts as crude climbs - Moneycontrol.com",
        "Nifty Midcap 100 hits all-time high even as Sensex, Nifty slide - Business Standard",
        "Sensex Today | Stock Market Highlights: Sensex tanks 1,456 points; Nifty ends below 23,400 - CNBC TV18",
        "Stock market: Sensex, Nifty outlook for tomorrow as NSE, BSE closed today for Bakri Id - Business Today",
        "Stock Market Outlook: How Will Nifty 50, Sensex Trade On May 27? - Republic World",
        "Stock Market Outlook Today, 27 May 2026: Sensex, Nifty Likely to Trade Volatile Amid US-Iran Tensions - Goodreturns",
        "Stock Market Update: Nifty 50, Sensex to Likely Open Lower, Key Levels to Watch - Analytics Insight",
        "Why did the stock market fall today? Sensex tumbles 1,300 pts, Nifty below 23,850. 6 key factors - The Economic Times",
        "Sensex & Nifty rally, Boosting Indian stock market by 13.8% in June quarter - News On AIR",
        "Stock market holiday today on May 28: BSE, NSE to remain closed today on account of Bakri Id/Eid al-Adha; Check full trading schedule - TradingView",
        "Share Market Today: Nifty 50, Bank Nifty Prediction | May 27, 2026 - Liquide Blog",
        "Nifty 50, Sensex prediction today: Check how Indian stock market is expected to trade on 27 May - Mint",
        "Sensex, Nifty opening: Will stock market continue its rally today? - India Today"
      ],
      "_vix_label": "VIX=15.0 [CALM <15 \u2192 +5]",
      "_futures_label": "ES=F -0.26% [FLAT \u2192 0]"
    },
    "scale_up": false,
    "_reason": ""
  }
]